politechie_core/__init__.py
politechie_core/utils/__init__.py
politechie_core/utils/base.py
politechie_core/utils/constants.py
politechie_core/validations/__init__.py
politechie_core/validations/age_validator.py
politechie_core/validations/dob_validator.py
politechie_core/validations/email_validator.py
politechie_core/validations/gender_validator.py
politechie_core/validations/phone_number_validator.py
politechie_core-0.1.3.dist-info/licenses/LICENSE
scripts/__init__.py
politechie_core-0.1.3.dist-info/METADATA
politechie_core-0.1.3.dist-info/WHEEL
politechie_core-0.1.3.dist-info/top_level.txt
politechie_core-0.1.3.dist-info/RECORD
