Metadata-Version: 2.4
Name: politechie_core
Version: 0.1.3
Summary: A validation library for phone numbers, email addresses, and dates of birth.
Home-page: https://github.com/politechielabs/politechie-core.git
Author: Palistha Deshar
Author-email: palisthadeshar@gmail.com
Classifier: Programming Language :: Python :: 3
Classifier: License :: OSI Approved :: MIT License
Classifier: Operating System :: OS Independent
Requires-Python: >=3.6
License-File: LICENSE
Dynamic: author
Dynamic: author-email
Dynamic: classifier
Dynamic: home-page
Dynamic: license-file
Dynamic: requires-python
Dynamic: summary
